<main version="1.3">
   <layoutName>F14</layoutName>
   <layoutSummary>Summary</layoutSummary>
   <rotation>0</rotation>
   <height>800</height>
   <width>600</width>
   <pad version="1.8" text="3">
      <OSCBundle>
         <OSCMessage>
            <OSCAddress>/sw/target3</OSCAddress>
            <OSCArgument version="1.2">
               <activeAxes>
                  <axis>
                     <number>1</number>
                     <active>false</active>
                  </axis>
                  <axis>
                     <number>2</number>
                     <active>false</active>
                  </axis>
                  <axis>
                     <number>3</number>
                     <active>false</active>
                  </axis>
               </activeAxes>
               <scalingAxes>
                  <axis>
                     <number>1</number>
                     <function>3</function>
                  </axis>
                  <axis>
                     <number>2</number>
                     <function>3</function>
                  </axis>
                  <axis>
                     <number>3</number>
                     <function>3</function>
                  </axis>
               </scalingAxes>
               <valueOfInteger>1</valueOfInteger>
               <refOfInteger>0</refOfInteger>
               <maxOfInteger>0</maxOfInteger>
               <defOfInteger>1</defOfInteger>
               <minOfInteger>0</minOfInteger>
               <isListening>false</isListening>
               <displayOnWidget>false</displayOnWidget>
            </OSCArgument>
         </OSCMessage>
      </OSCBundle>
      <colors>
         <foreColor>-1</foreColor>
         <backColor>-1</backColor>
         <textColor>-16777216</textColor>
         <borderColor>-12566464</borderColor>
         <foreAlpha>255</foreAlpha>
         <backAlpha>255</backAlpha>
         <textAlpha>255</textAlpha>
         <borderAlpha>255</borderAlpha>
      </colors>
      <Z>3</Z>
      <X>230</X>
      <Y>426</Y>
      <width>39</width>
      <height>48</height>
      <borderwidth>2</borderwidth>
      <smoothingFactor>10.0</smoothingFactor>
      <rotation>0.0</rotation>
      <isTouchable>true</isTouchable>
      <displayName>true</displayName>
      <localFeedback>false</localFeedback>
      <isSliding>false</isSliding>
      <isRelative>false</isRelative>
      <contForeImg>false</contForeImg>
      <font>Arial-plain-12</font>
      <backgroundImage> </backgroundImage>
      <foregroundImage> </foregroundImage>
   </pad>
   <pad version="1.8" text="4">
      <OSCBundle>
         <OSCMessage>
            <OSCAddress>/sw/target4</OSCAddress>
            <OSCArgument version="1.2">
               <activeAxes>
                  <axis>
                     <number>1</number>
                     <active>false</active>
                  </axis>
                  <axis>
                     <number>2</number>
                     <active>false</active>
                  </axis>
                  <axis>
                     <number>3</number>
                     <active>false</active>
                  </axis>
               </activeAxes>
               <scalingAxes>
                  <axis>
                     <number>1</number>
                     <function>3</function>
                  </axis>
                  <axis>
                     <number>2</number>
                     <function>3</function>
                  </axis>
                  <axis>
                     <number>3</number>
                     <function>3</function>
                  </axis>
               </scalingAxes>
               <valueOfInteger>1</valueOfInteger>
               <refOfInteger>0</refOfInteger>
               <maxOfInteger>0</maxOfInteger>
               <defOfInteger>1</defOfInteger>
               <minOfInteger>0</minOfInteger>
               <isListening>false</isListening>
               <displayOnWidget>false</displayOnWidget>
            </OSCArgument>
         </OSCMessage>
      </OSCBundle>
      <colors>
         <foreColor>-1</foreColor>
         <backColor>-1</backColor>
         <textColor>-16777216</textColor>
         <borderColor>-12566464</borderColor>
         <foreAlpha>255</foreAlpha>
         <backAlpha>255</backAlpha>
         <textAlpha>255</textAlpha>
         <borderAlpha>255</borderAlpha>
      </colors>
      <Z>2</Z>
      <X>294</X>
      <Y>426</Y>
      <width>39</width>
      <height>48</height>
      <borderwidth>2</borderwidth>
      <smoothingFactor>10.0</smoothingFactor>
      <rotation>0.0</rotation>
      <isTouchable>true</isTouchable>
      <displayName>true</displayName>
      <localFeedback>false</localFeedback>
      <isSliding>false</isSliding>
      <isRelative>false</isRelative>
      <contForeImg>false</contForeImg>
      <font>Arial-plain-12</font>
      <backgroundImage> </backgroundImage>
      <foregroundImage> </foregroundImage>
   </pad>
   <pad version="1.8" text="5">
      <OSCBundle>
         <OSCMessage>
            <OSCAddress>/sw/target5</OSCAddress>
            <OSCArgument version="1.2">
               <activeAxes>
                  <axis>
                     <number>1</number>
                     <active>false</active>
                  </axis>
                  <axis>
                     <number>2</number>
                     <active>false</active>
                  </axis>
                  <axis>
                     <number>3</number>
                     <active>false</active>
                  </axis>
               </activeAxes>
               <scalingAxes>
                  <axis>
                     <number>1</number>
                     <function>3</function>
                  </axis>
                  <axis>
                     <number>2</number>
                     <function>3</function>
                  </axis>
                  <axis>
                     <number>3</number>
                     <function>3</function>
                  </axis>
               </scalingAxes>
               <valueOfInteger>1</valueOfInteger>
               <refOfInteger>0</refOfInteger>
               <maxOfInteger>0</maxOfInteger>
               <defOfInteger>1</defOfInteger>
               <minOfInteger>0</minOfInteger>
               <isListening>false</isListening>
               <displayOnWidget>false</displayOnWidget>
            </OSCArgument>
         </OSCMessage>
      </OSCBundle>
      <colors>
         <foreColor>-1</foreColor>
         <backColor>-1</backColor>
         <textColor>-16777216</textColor>
         <borderColor>-12566464</borderColor>
         <foreAlpha>255</foreAlpha>
         <backAlpha>255</backAlpha>
         <textAlpha>255</textAlpha>
         <borderAlpha>255</borderAlpha>
      </colors>
      <Z>1</Z>
      <X>305</X>
      <Y>371</Y>
      <width>39</width>
      <height>48</height>
      <borderwidth>2</borderwidth>
      <smoothingFactor>10.0</smoothingFactor>
      <rotation>0.0</rotation>
      <isTouchable>true</isTouchable>
      <displayName>true</displayName>
      <localFeedback>false</localFeedback>
      <isSliding>false</isSliding>
      <isRelative>false</isRelative>
      <contForeImg>false</contForeImg>
      <font>Arial-plain-12</font>
      <backgroundImage> </backgroundImage>
      <foregroundImage> </foregroundImage>
   </pad>
   <pad version="1.8" text="6">
      <OSCBundle>
         <OSCMessage>
            <OSCAddress>/sw/target6</OSCAddress>
            <OSCArgument version="1.2">
               <activeAxes>
                  <axis>
                     <number>1</number>
                     <active>false</active>
                  </axis>
                  <axis>
                     <number>2</number>
                     <active>false</active>
                  </axis>
                  <axis>
                     <number>3</number>
                     <active>false</active>
                  </axis>
               </activeAxes>
               <scalingAxes>
                  <axis>
                     <number>1</number>
                     <function>3</function>
                  </axis>
                  <axis>
                     <number>2</number>
                     <function>3</function>
                  </axis>
                  <axis>
                     <number>3</number>
                     <function>3</function>
                  </axis>
               </scalingAxes>
               <valueOfInteger>1</valueOfInteger>
               <refOfInteger>0</refOfInteger>
               <maxOfInteger>0</maxOfInteger>
               <defOfInteger>1</defOfInteger>
               <minOfInteger>0</minOfInteger>
               <isListening>false</isListening>
               <displayOnWidget>false</displayOnWidget>
            </OSCArgument>
         </OSCMessage>
      </OSCBundle>
      <colors>
         <foreColor>-1</foreColor>
         <backColor>-1</backColor>
         <textColor>-16777216</textColor>
         <borderColor>-12566464</borderColor>
         <foreAlpha>255</foreAlpha>
         <backAlpha>255</backAlpha>
         <textAlpha>255</textAlpha>
         <borderAlpha>255</borderAlpha>
      </colors>
      <Z>0</Z>
      <X>318</X>
      <Y>318</Y>
      <width>39</width>
      <height>48</height>
      <borderwidth>2</borderwidth>
      <smoothingFactor>10.0</smoothingFactor>
      <rotation>0.0</rotation>
      <isTouchable>true</isTouchable>
      <displayName>true</displayName>
      <localFeedback>false</localFeedback>
      <isSliding>false</isSliding>
      <isRelative>false</isRelative>
      <contForeImg>false</contForeImg>
      <font>Arial-plain-12</font>
      <backgroundImage> </backgroundImage>
      <foregroundImage> </foregroundImage>
   </pad>
   <pad version="1.8" text="C">
      <OSCBundle>
         <OSCMessage>
            <OSCAddress>/sw/lowerRightC</OSCAddress>
            <OSCArgument version="1.2">
               <activeAxes>
                  <axis>
                     <number>1</number>
                     <active>false</active>
                  </axis>
                  <axis>
                     <number>2</number>
                     <active>false</active>
                  </axis>
                  <axis>
                     <number>3</number>
                     <active>false</active>
                  </axis>
               </activeAxes>
               <scalingAxes>
                  <axis>
                     <number>1</number>
                     <function>3</function>
                  </axis>
                  <axis>
                     <number>2</number>
                     <function>3</function>
                  </axis>
                  <axis>
                     <number>3</number>
                     <function>3</function>
                  </axis>
               </scalingAxes>
               <valueOfInteger>1</valueOfInteger>
               <refOfInteger>0</refOfInteger>
               <maxOfInteger>0</maxOfInteger>
               <defOfInteger>1</defOfInteger>
               <minOfInteger>0</minOfInteger>
               <isListening>false</isListening>
               <displayOnWidget>false</displayOnWidget>
            </OSCArgument>
         </OSCMessage>
      </OSCBundle>
      <colors>
         <foreColor>-16763905</foreColor>
         <backColor>-16776961</backColor>
         <textColor>-1</textColor>
         <borderColor>-12566464</borderColor>
         <foreAlpha>255</foreAlpha>
         <backAlpha>255</backAlpha>
         <textAlpha>255</textAlpha>
         <borderAlpha>255</borderAlpha>
      </colors>
      <Z>18</Z>
      <X>433</X>
      <Y>352</Y>
      <width>39</width>
      <height>48</height>
      <borderwidth>2</borderwidth>
      <smoothingFactor>10.0</smoothingFactor>
      <rotation>50.0</rotation>
      <isTouchable>true</isTouchable>
      <displayName>true</displayName>
      <localFeedback>false</localFeedback>
      <isSliding>false</isSliding>
      <isRelative>false</isRelative>
      <contForeImg>false</contForeImg>
      <font>Arial-plain-12</font>
      <backgroundImage> </backgroundImage>
      <foregroundImage> </foregroundImage>
   </pad>
   <pad version="1.8" text="A">
      <OSCBundle>
         <OSCMessage>
            <OSCAddress>/sw/lowerRightA</OSCAddress>
            <OSCArgument version="1.2">
               <activeAxes>
                  <axis>
                     <number>1</number>
                     <active>false</active>
                  </axis>
                  <axis>
                     <number>2</number>
                     <active>false</active>
                  </axis>
                  <axis>
                     <number>3</number>
                     <active>false</active>
                  </axis>
               </activeAxes>
               <scalingAxes>
                  <axis>
                     <number>1</number>
                     <function>3</function>
                  </axis>
                  <axis>
                     <number>2</number>
                     <function>3</function>
                  </axis>
                  <axis>
                     <number>3</number>
                     <function>3</function>
                  </axis>
               </scalingAxes>
               <valueOfInteger>1</valueOfInteger>
               <refOfInteger>0</refOfInteger>
               <maxOfInteger>0</maxOfInteger>
               <defOfInteger>1</defOfInteger>
               <minOfInteger>0</minOfInteger>
               <isListening>false</isListening>
               <displayOnWidget>false</displayOnWidget>
            </OSCArgument>
         </OSCMessage>
      </OSCBundle>
      <colors>
         <foreColor>-16763905</foreColor>
         <backColor>-16776961</backColor>
         <textColor>-1</textColor>
         <borderColor>-12566464</borderColor>
         <foreAlpha>255</foreAlpha>
         <backAlpha>255</backAlpha>
         <textAlpha>255</textAlpha>
         <borderAlpha>255</borderAlpha>
      </colors>
      <Z>17</Z>
      <X>435</X>
      <Y>406</Y>
      <width>39</width>
      <height>48</height>
      <borderwidth>2</borderwidth>
      <smoothingFactor>10.0</smoothingFactor>
      <rotation>50.0</rotation>
      <isTouchable>true</isTouchable>
      <displayName>true</displayName>
      <localFeedback>false</localFeedback>
      <isSliding>false</isSliding>
      <isRelative>false</isRelative>
      <contForeImg>false</contForeImg>
      <font>Arial-plain-12</font>
      <backgroundImage> </backgroundImage>
      <foregroundImage> </foregroundImage>
   </pad>
   <pad version="1.8" text="T">
      <OSCBundle>
         <OSCMessage>
            <OSCAddress>/sw/lowerRightT</OSCAddress>
            <OSCArgument version="1.2">
               <activeAxes>
                  <axis>
                     <number>1</number>
                     <active>false</active>
                  </axis>
                  <axis>
                     <number>2</number>
                     <active>false</active>
                  </axis>
                  <axis>
                     <number>3</number>
                     <active>false</active>
                  </axis>
               </activeAxes>
               <scalingAxes>
                  <axis>
                     <number>1</number>
                     <function>3</function>
                  </axis>
                  <axis>
                     <number>2</number>
                     <function>3</function>
                  </axis>
                  <axis>
                     <number>3</number>
                     <function>3</function>
                  </axis>
               </scalingAxes>
               <valueOfInteger>1</valueOfInteger>
               <refOfInteger>0</refOfInteger>
               <maxOfInteger>0</maxOfInteger>
               <defOfInteger>1</defOfInteger>
               <minOfInteger>0</minOfInteger>
               <isListening>false</isListening>
               <displayOnWidget>false</displayOnWidget>
            </OSCArgument>
         </OSCMessage>
      </OSCBundle>
      <colors>
         <foreColor>-16763905</foreColor>
         <backColor>-16776961</backColor>
         <textColor>-1</textColor>
         <borderColor>-12566464</borderColor>
         <foreAlpha>255</foreAlpha>
         <backAlpha>255</backAlpha>
         <textAlpha>255</textAlpha>
         <borderAlpha>255</borderAlpha>
      </colors>
      <Z>16</Z>
      <X>436</X>
      <Y>458</Y>
      <width>39</width>
      <height>48</height>
      <borderwidth>2</borderwidth>
      <smoothingFactor>10.0</smoothingFactor>
      <rotation>50.0</rotation>
      <isTouchable>true</isTouchable>
      <displayName>true</displayName>
      <localFeedback>false</localFeedback>
      <isSliding>false</isSliding>
      <isRelative>false</isRelative>
      <contForeImg>false</contForeImg>
      <font>Arial-plain-12</font>
      <backgroundImage> </backgroundImage>
      <foregroundImage> </foregroundImage>
   </pad>
   <pad version="1.8" text="A">
      <OSCBundle>
         <OSCMessage>
            <OSCAddress>/sw/upperRightA</OSCAddress>
            <OSCArgument version="1.2">
               <activeAxes>
                  <axis>
                     <number>1</number>
                     <active>false</active>
                  </axis>
                  <axis>
                     <number>2</number>
                     <active>false</active>
                  </axis>
                  <axis>
                     <number>3</number>
                     <active>false</active>
                  </axis>
               </activeAxes>
               <scalingAxes>
                  <axis>
                     <number>1</number>
                     <function>3</function>
                  </axis>
                  <axis>
                     <number>2</number>
                     <function>3</function>
                  </axis>
                  <axis>
                     <number>3</number>
                     <function>3</function>
                  </axis>
               </scalingAxes>
               <valueOfInteger>1</valueOfInteger>
               <refOfInteger>0</refOfInteger>
               <maxOfInteger>0</maxOfInteger>
               <defOfInteger>1</defOfInteger>
               <minOfInteger>0</minOfInteger>
               <isListening>false</isListening>
               <displayOnWidget>false</displayOnWidget>
            </OSCArgument>
         </OSCMessage>
      </OSCBundle>
      <colors>
         <foreColor>-16763905</foreColor>
         <backColor>-16776961</backColor>
         <textColor>-1</textColor>
         <borderColor>-12566464</borderColor>
         <foreAlpha>255</foreAlpha>
         <backAlpha>255</backAlpha>
         <textAlpha>255</textAlpha>
         <borderAlpha>255</borderAlpha>
      </colors>
      <Z>19</Z>
      <X>397</X>
      <Y>181</Y>
      <width>39</width>
      <height>48</height>
      <borderwidth>2</borderwidth>
      <smoothingFactor>10.0</smoothingFactor>
      <rotation>50.0</rotation>
      <isTouchable>true</isTouchable>
      <displayName>true</displayName>
      <localFeedback>false</localFeedback>
      <isSliding>false</isSliding>
      <isRelative>false</isRelative>
      <contForeImg>false</contForeImg>
      <font>Arial-plain-12</font>
      <backgroundImage> </backgroundImage>
      <foregroundImage> </foregroundImage>
   </pad>
   <pad version="1.8" text="T">
      <OSCBundle>
         <OSCMessage>
            <OSCAddress>/sw/lowerLeftT</OSCAddress>
            <OSCArgument version="1.2">
               <activeAxes>
                  <axis>
                     <number>1</number>
                     <active>false</active>
                  </axis>
                  <axis>
                     <number>2</number>
                     <active>false</active>
                  </axis>
                  <axis>
                     <number>3</number>
                     <active>false</active>
                  </axis>
               </activeAxes>
               <scalingAxes>
                  <axis>
                     <number>1</number>
                     <function>3</function>
                  </axis>
                  <axis>
                     <number>2</number>
                     <function>3</function>
                  </axis>
                  <axis>
                     <number>3</number>
                     <function>3</function>
                  </axis>
               </scalingAxes>
               <valueOfInteger>1</valueOfInteger>
               <refOfInteger>0</refOfInteger>
               <maxOfInteger>0</maxOfInteger>
               <defOfInteger>1</defOfInteger>
               <minOfInteger>0</minOfInteger>
               <isListening>false</isListening>
               <displayOnWidget>false</displayOnWidget>
            </OSCArgument>
         </OSCMessage>
      </OSCBundle>
      <colors>
         <foreColor>-50116</foreColor>
         <backColor>-65536</backColor>
         <textColor>-1</textColor>
         <borderColor>-12566464</borderColor>
         <foreAlpha>255</foreAlpha>
         <backAlpha>255</backAlpha>
         <textAlpha>255</textAlpha>
         <borderAlpha>255</borderAlpha>
      </colors>
      <Z>15</Z>
      <X>119</X>
      <Y>464</Y>
      <width>39</width>
      <height>48</height>
      <borderwidth>2</borderwidth>
      <smoothingFactor>10.0</smoothingFactor>
      <rotation>310.0</rotation>
      <isTouchable>true</isTouchable>
      <displayName>true</displayName>
      <localFeedback>false</localFeedback>
      <isSliding>false</isSliding>
      <isRelative>false</isRelative>
      <contForeImg>false</contForeImg>
      <font>Arial-plain-12</font>
      <backgroundImage> </backgroundImage>
      <foregroundImage> </foregroundImage>
   </pad>
   <pad version="1.8" text="Yagov">
      <OSCBundle>
         <OSCMessage>
            <OSCAddress>/sw/yagov</OSCAddress>
            <OSCArgument version="1.2">
               <activeAxes>
                  <axis>
                     <number>1</number>
                     <active>false</active>
                  </axis>
                  <axis>
                     <number>2</number>
                     <active>false</active>
                  </axis>
                  <axis>
                     <number>3</number>
                     <active>false</active>
                  </axis>
               </activeAxes>
               <scalingAxes>
                  <axis>
                     <number>1</number>
                     <function>3</function>
                  </axis>
                  <axis>
                     <number>2</number>
                     <function>3</function>
                  </axis>
                  <axis>
                     <number>3</number>
                     <function>3</function>
                  </axis>
               </scalingAxes>
               <valueOfInteger>1</valueOfInteger>
               <refOfInteger>0</refOfInteger>
               <maxOfInteger>0</maxOfInteger>
               <defOfInteger>1</defOfInteger>
               <minOfInteger>0</minOfInteger>
               <isListening>false</isListening>
               <displayOnWidget>false</displayOnWidget>
            </OSCArgument>
         </OSCMessage>
      </OSCBundle>
      <colors>
         <foreColor>-50116</foreColor>
         <backColor>-65536</backColor>
         <textColor>-1</textColor>
         <borderColor>-12566464</borderColor>
         <foreAlpha>255</foreAlpha>
         <backAlpha>255</backAlpha>
         <textAlpha>255</textAlpha>
         <borderAlpha>255</borderAlpha>
      </colors>
      <Z>14</Z>
      <X>58</X>
      <Y>83</Y>
      <width>45</width>
      <height>74</height>
      <borderwidth>2</borderwidth>
      <smoothingFactor>10.0</smoothingFactor>
      <rotation>0.0</rotation>
      <isTouchable>true</isTouchable>
      <displayName>true</displayName>
      <localFeedback>false</localFeedback>
      <isSliding>false</isSliding>
      <isRelative>false</isRelative>
      <contForeImg>false</contForeImg>
      <font>Arial-plain-12</font>
      <backgroundImage> </backgroundImage>
      <foregroundImage> </foregroundImage>
   </pad>
   <pad version="1.8" text="O">
      <OSCBundle>
         <OSCMessage>
            <OSCAddress>/sw/lowerLeftO</OSCAddress>
            <OSCArgument version="1.2">
               <activeAxes>
                  <axis>
                     <number>1</number>
                     <active>false</active>
                  </axis>
                  <axis>
                     <number>2</number>
                     <active>false</active>
                  </axis>
                  <axis>
                     <number>3</number>
                     <active>false</active>
                  </axis>
               </activeAxes>
               <scalingAxes>
                  <axis>
                     <number>1</number>
                     <function>3</function>
                  </axis>
                  <axis>
                     <number>2</number>
                     <function>3</function>
                  </axis>
                  <axis>
                     <number>3</number>
                     <function>3</function>
                  </axis>
               </scalingAxes>
               <valueOfInteger>1</valueOfInteger>
               <refOfInteger>0</refOfInteger>
               <maxOfInteger>0</maxOfInteger>
               <defOfInteger>1</defOfInteger>
               <minOfInteger>0</minOfInteger>
               <isListening>false</isListening>
               <displayOnWidget>false</displayOnWidget>
            </OSCArgument>
         </OSCMessage>
      </OSCBundle>
      <colors>
         <foreColor>-50116</foreColor>
         <backColor>-65536</backColor>
         <textColor>-1</textColor>
         <borderColor>-12566464</borderColor>
         <foreAlpha>255</foreAlpha>
         <backAlpha>255</backAlpha>
         <textAlpha>255</textAlpha>
         <borderAlpha>255</borderAlpha>
      </colors>
      <Z>13</Z>
      <X>118</X>
      <Y>412</Y>
      <width>39</width>
      <height>48</height>
      <borderwidth>2</borderwidth>
      <smoothingFactor>10.0</smoothingFactor>
      <rotation>310.0</rotation>
      <isTouchable>true</isTouchable>
      <displayName>true</displayName>
      <localFeedback>false</localFeedback>
      <isSliding>false</isSliding>
      <isRelative>false</isRelative>
      <contForeImg>false</contForeImg>
      <font>Arial-plain-12</font>
      <backgroundImage> </backgroundImage>
      <foregroundImage> </foregroundImage>
   </pad>
   <pad version="1.8" text="M">
      <OSCBundle>
         <OSCMessage>
            <OSCAddress>/sw/lowerLeftM</OSCAddress>
            <OSCArgument version="1.2">
               <activeAxes>
                  <axis>
                     <number>1</number>
                     <active>false</active>
                  </axis>
                  <axis>
                     <number>2</number>
                     <active>false</active>
                  </axis>
                  <axis>
                     <number>3</number>
                     <active>false</active>
                  </axis>
               </activeAxes>
               <scalingAxes>
                  <axis>
                     <number>1</number>
                     <function>3</function>
                  </axis>
                  <axis>
                     <number>2</number>
                     <function>3</function>
                  </axis>
                  <axis>
                     <number>3</number>
                     <function>3</function>
                  </axis>
               </scalingAxes>
               <valueOfInteger>1</valueOfInteger>
               <refOfInteger>0</refOfInteger>
               <maxOfInteger>0</maxOfInteger>
               <defOfInteger>1</defOfInteger>
               <minOfInteger>0</minOfInteger>
               <isListening>false</isListening>
               <displayOnWidget>false</displayOnWidget>
            </OSCArgument>
         </OSCMessage>
      </OSCBundle>
      <colors>
         <foreColor>-50116</foreColor>
         <backColor>-65536</backColor>
         <textColor>-1</textColor>
         <borderColor>-12566464</borderColor>
         <foreAlpha>255</foreAlpha>
         <backAlpha>255</backAlpha>
         <textAlpha>255</textAlpha>
         <borderAlpha>255</borderAlpha>
      </colors>
      <Z>12</Z>
      <X>117</X>
      <Y>358</Y>
      <width>39</width>
      <height>48</height>
      <borderwidth>2</borderwidth>
      <smoothingFactor>10.0</smoothingFactor>
      <rotation>310.0</rotation>
      <isTouchable>true</isTouchable>
      <displayName>true</displayName>
      <localFeedback>false</localFeedback>
      <isSliding>false</isSliding>
      <isRelative>false</isRelative>
      <contForeImg>false</contForeImg>
      <font>Arial-plain-12</font>
      <backgroundImage> </backgroundImage>
      <foregroundImage> </foregroundImage>
   </pad>
   <pad version="1.8" text="1">
      <OSCBundle>
         <OSCMessage>
            <OSCAddress>/sw/target1</OSCAddress>
            <OSCArgument version="1.2">
               <activeAxes>
                  <axis>
                     <number>1</number>
                     <active>false</active>
                  </axis>
                  <axis>
                     <number>2</number>
                     <active>false</active>
                  </axis>
                  <axis>
                     <number>3</number>
                     <active>false</active>
                  </axis>
               </activeAxes>
               <scalingAxes>
                  <axis>
                     <number>1</number>
                     <function>3</function>
                  </axis>
                  <axis>
                     <number>2</number>
                     <function>3</function>
                  </axis>
                  <axis>
                     <number>3</number>
                     <function>3</function>
                  </axis>
               </scalingAxes>
               <valueOfInteger>1</valueOfInteger>
               <refOfInteger>0</refOfInteger>
               <maxOfInteger>0</maxOfInteger>
               <defOfInteger>1</defOfInteger>
               <minOfInteger>0</minOfInteger>
               <isListening>false</isListening>
               <displayOnWidget>false</displayOnWidget>
            </OSCArgument>
         </OSCMessage>
      </OSCBundle>
      <colors>
         <foreColor>-1</foreColor>
         <backColor>-1</backColor>
         <textColor>-16777216</textColor>
         <borderColor>-12566464</borderColor>
         <foreAlpha>255</foreAlpha>
         <backAlpha>255</backAlpha>
         <textAlpha>255</textAlpha>
         <borderAlpha>255</borderAlpha>
      </colors>
      <Z>11</Z>
      <X>209</X>
      <Y>319</Y>
      <width>39</width>
      <height>48</height>
      <borderwidth>2</borderwidth>
      <smoothingFactor>10.0</smoothingFactor>
      <rotation>0.0</rotation>
      <isTouchable>true</isTouchable>
      <displayName>true</displayName>
      <localFeedback>false</localFeedback>
      <isSliding>false</isSliding>
      <isRelative>false</isRelative>
      <contForeImg>false</contForeImg>
      <font>Arial-plain-12</font>
      <backgroundImage> </backgroundImage>
      <foregroundImage> </foregroundImage>
   </pad>
   <pad version="1.8" text="Inlane">
      <OSCBundle>
         <OSCMessage>
            <OSCAddress>/sw/inlaneLeft</OSCAddress>
            <OSCArgument version="1.2">
               <activeAxes>
                  <axis>
                     <number>1</number>
                     <active>false</active>
                  </axis>
                  <axis>
                     <number>2</number>
                     <active>false</active>
                  </axis>
                  <axis>
                     <number>3</number>
                     <active>false</active>
                  </axis>
               </activeAxes>
               <scalingAxes>
                  <axis>
                     <number>1</number>
                     <function>3</function>
                  </axis>
                  <axis>
                     <number>2</number>
                     <function>3</function>
                  </axis>
                  <axis>
                     <number>3</number>
                     <function>3</function>
                  </axis>
               </scalingAxes>
               <valueOfInteger>1</valueOfInteger>
               <refOfInteger>0</refOfInteger>
               <maxOfInteger>0</maxOfInteger>
               <defOfInteger>1</defOfInteger>
               <minOfInteger>0</minOfInteger>
               <isListening>false</isListening>
               <displayOnWidget>false</displayOnWidget>
            </OSCArgument>
         </OSCMessage>
      </OSCBundle>
      <colors>
         <foreColor>-1</foreColor>
         <backColor>-1</backColor>
         <textColor>-16777216</textColor>
         <borderColor>-12566464</borderColor>
         <foreAlpha>255</foreAlpha>
         <backAlpha>255</backAlpha>
         <textAlpha>255</textAlpha>
         <borderAlpha>255</borderAlpha>
      </colors>
      <Z>10</Z>
      <X>146</X>
      <Y>586</Y>
      <width>49</width>
      <height>48</height>
      <borderwidth>2</borderwidth>
      <smoothingFactor>10.0</smoothingFactor>
      <rotation>0.0</rotation>
      <isTouchable>true</isTouchable>
      <displayName>true</displayName>
      <localFeedback>false</localFeedback>
      <isSliding>false</isSliding>
      <isRelative>false</isRelative>
      <contForeImg>false</contForeImg>
      <font>Arial-plain-12</font>
      <backgroundImage> </backgroundImage>
      <foregroundImage> </foregroundImage>
   </pad>
   <pad version="1.8" text="Inlane">
      <OSCBundle>
         <OSCMessage>
            <OSCAddress>/sw/inlaneRight</OSCAddress>
            <OSCArgument version="1.2">
               <activeAxes>
                  <axis>
                     <number>1</number>
                     <active>false</active>
                  </axis>
                  <axis>
                     <number>2</number>
                     <active>false</active>
                  </axis>
                  <axis>
                     <number>3</number>
                     <active>false</active>
                  </axis>
               </activeAxes>
               <scalingAxes>
                  <axis>
                     <number>1</number>
                     <function>3</function>
                  </axis>
                  <axis>
                     <number>2</number>
                     <function>3</function>
                  </axis>
                  <axis>
                     <number>3</number>
                     <function>3</function>
                  </axis>
               </scalingAxes>
               <valueOfInteger>1</valueOfInteger>
               <refOfInteger>0</refOfInteger>
               <maxOfInteger>0</maxOfInteger>
               <defOfInteger>1</defOfInteger>
               <minOfInteger>0</minOfInteger>
               <isListening>false</isListening>
               <displayOnWidget>false</displayOnWidget>
            </OSCArgument>
         </OSCMessage>
      </OSCBundle>
      <colors>
         <foreColor>-1</foreColor>
         <backColor>-1</backColor>
         <textColor>-16777216</textColor>
         <borderColor>-12566464</borderColor>
         <foreAlpha>255</foreAlpha>
         <backAlpha>255</backAlpha>
         <textAlpha>255</textAlpha>
         <borderAlpha>255</borderAlpha>
      </colors>
      <Z>9</Z>
      <X>422</X>
      <Y>585</Y>
      <width>49</width>
      <height>48</height>
      <borderwidth>2</borderwidth>
      <smoothingFactor>10.0</smoothingFactor>
      <rotation>0.0</rotation>
      <isTouchable>true</isTouchable>
      <displayName>true</displayName>
      <localFeedback>false</localFeedback>
      <isSliding>false</isSliding>
      <isRelative>false</isRelative>
      <contForeImg>false</contForeImg>
      <font>Arial-plain-12</font>
      <backgroundImage> </backgroundImage>
      <foregroundImage> </foregroundImage>
   </pad>
   <pad version="1.8" text="X">
      <OSCBundle>
         <OSCMessage>
            <OSCAddress>/sw/bonusXLeft</OSCAddress>
            <OSCArgument version="1.2">
               <activeAxes>
                  <axis>
                     <number>1</number>
                     <active>false</active>
                  </axis>
                  <axis>
                     <number>2</number>
                     <active>false</active>
                  </axis>
                  <axis>
                     <number>3</number>
                     <active>false</active>
                  </axis>
               </activeAxes>
               <scalingAxes>
                  <axis>
                     <number>1</number>
                     <function>3</function>
                  </axis>
                  <axis>
                     <number>2</number>
                     <function>3</function>
                  </axis>
                  <axis>
                     <number>3</number>
                     <function>3</function>
                  </axis>
               </scalingAxes>
               <valueOfInteger>1</valueOfInteger>
               <refOfInteger>0</refOfInteger>
               <maxOfInteger>0</maxOfInteger>
               <defOfInteger>1</defOfInteger>
               <minOfInteger>0</minOfInteger>
               <isListening>false</isListening>
               <displayOnWidget>false</displayOnWidget>
            </OSCArgument>
         </OSCMessage>
      </OSCBundle>
      <colors>
         <foreColor>-39424</foreColor>
         <backColor>-39936</backColor>
         <textColor>-16777216</textColor>
         <borderColor>-12566464</borderColor>
         <foreAlpha>255</foreAlpha>
         <backAlpha>255</backAlpha>
         <textAlpha>255</textAlpha>
         <borderAlpha>255</borderAlpha>
      </colors>
      <Z>8</Z>
      <X>176</X>
      <Y>80</Y>
      <width>39</width>
      <height>48</height>
      <borderwidth>2</borderwidth>
      <smoothingFactor>10.0</smoothingFactor>
      <rotation>0.0</rotation>
      <isTouchable>true</isTouchable>
      <displayName>true</displayName>
      <localFeedback>false</localFeedback>
      <isSliding>false</isSliding>
      <isRelative>false</isRelative>
      <contForeImg>false</contForeImg>
      <font>Arial-plain-12</font>
      <backgroundImage> </backgroundImage>
      <foregroundImage> </foregroundImage>
   </pad>
   <pad version="1.8" text="R">
      <OSCBundle>
         <OSCMessage>
            <OSCAddress>/sw/rightRescue</OSCAddress>
            <OSCArgument version="1.2">
               <activeAxes>
                  <axis>
                     <number>1</number>
                     <active>false</active>
                  </axis>
                  <axis>
                     <number>2</number>
                     <active>false</active>
                  </axis>
                  <axis>
                     <number>3</number>
                     <active>false</active>
                  </axis>
               </activeAxes>
               <scalingAxes>
                  <axis>
                     <number>1</number>
                     <function>3</function>
                  </axis>
                  <axis>
                     <number>2</number>
                     <function>3</function>
                  </axis>
                  <axis>
                     <number>3</number>
                     <function>3</function>
                  </axis>
               </scalingAxes>
               <valueOfInteger>1</valueOfInteger>
               <refOfInteger>0</refOfInteger>
               <maxOfInteger>0</maxOfInteger>
               <defOfInteger>1</defOfInteger>
               <minOfInteger>0</minOfInteger>
               <isListening>false</isListening>
               <displayOnWidget>false</displayOnWidget>
            </OSCArgument>
         </OSCMessage>
      </OSCBundle>
      <colors>
         <foreColor>-39424</foreColor>
         <backColor>-39936</backColor>
         <textColor>-16777216</textColor>
         <borderColor>-12566464</borderColor>
         <foreAlpha>255</foreAlpha>
         <backAlpha>255</backAlpha>
         <textAlpha>255</textAlpha>
         <borderAlpha>255</borderAlpha>
      </colors>
      <Z>7</Z>
      <X>287</X>
      <Y>481</Y>
      <width>39</width>
      <height>48</height>
      <borderwidth>2</borderwidth>
      <smoothingFactor>10.0</smoothingFactor>
      <rotation>0.0</rotation>
      <isTouchable>true</isTouchable>
      <displayName>true</displayName>
      <localFeedback>false</localFeedback>
      <isSliding>false</isSliding>
      <isRelative>false</isRelative>
      <contForeImg>false</contForeImg>
      <font>Arial-plain-12</font>
      <backgroundImage> </backgroundImage>
      <foregroundImage> </foregroundImage>
   </pad>
   <pad version="1.8" text="L">
      <OSCBundle>
         <OSCMessage>
            <OSCAddress>/sw/leftRescue</OSCAddress>
            <OSCArgument version="1.2">
               <activeAxes>
                  <axis>
                     <number>1</number>
                     <active>false</active>
                  </axis>
                  <axis>
                     <number>2</number>
                     <active>false</active>
                  </axis>
                  <axis>
                     <number>3</number>
                     <active>false</active>
                  </axis>
               </activeAxes>
               <scalingAxes>
                  <axis>
                     <number>1</number>
                     <function>3</function>
                  </axis>
                  <axis>
                     <number>2</number>
                     <function>3</function>
                  </axis>
                  <axis>
                     <number>3</number>
                     <function>3</function>
                  </axis>
               </scalingAxes>
               <valueOfInteger>1</valueOfInteger>
               <refOfInteger>0</refOfInteger>
               <maxOfInteger>0</maxOfInteger>
               <defOfInteger>1</defOfInteger>
               <minOfInteger>0</minOfInteger>
               <isListening>false</isListening>
               <displayOnWidget>false</displayOnWidget>
            </OSCArgument>
         </OSCMessage>
      </OSCBundle>
      <colors>
         <foreColor>-39424</foreColor>
         <backColor>-39936</backColor>
         <textColor>-16777216</textColor>
         <borderColor>-12566464</borderColor>
         <foreAlpha>255</foreAlpha>
         <backAlpha>255</backAlpha>
         <textAlpha>255</textAlpha>
         <borderAlpha>255</borderAlpha>
      </colors>
      <Z>6</Z>
      <X>239</X>
      <Y>480</Y>
      <width>39</width>
      <height>48</height>
      <borderwidth>2</borderwidth>
      <smoothingFactor>10.0</smoothingFactor>
      <rotation>0.0</rotation>
      <isTouchable>true</isTouchable>
      <displayName>true</displayName>
      <localFeedback>false</localFeedback>
      <isSliding>false</isSliding>
      <isRelative>false</isRelative>
      <contForeImg>false</contForeImg>
      <font>Arial-plain-12</font>
      <backgroundImage> </backgroundImage>
      <foregroundImage> </foregroundImage>
   </pad>
   <pad version="1.8" text="X">
      <OSCBundle>
         <OSCMessage>
            <OSCAddress>/sw/bonusXRight</OSCAddress>
            <OSCArgument version="1.2">
               <activeAxes>
                  <axis>
                     <number>1</number>
                     <active>false</active>
                  </axis>
                  <axis>
                     <number>2</number>
                     <active>false</active>
                  </axis>
                  <axis>
                     <number>3</number>
                     <active>false</active>
                  </axis>
               </activeAxes>
               <scalingAxes>
                  <axis>
                     <number>1</number>
                     <function>3</function>
                  </axis>
                  <axis>
                     <number>2</number>
                     <function>3</function>
                  </axis>
                  <axis>
                     <number>3</number>
                     <function>3</function>
                  </axis>
               </scalingAxes>
               <valueOfInteger>1</valueOfInteger>
               <refOfInteger>0</refOfInteger>
               <maxOfInteger>0</maxOfInteger>
               <defOfInteger>1</defOfInteger>
               <minOfInteger>0</minOfInteger>
               <isListening>false</isListening>
               <displayOnWidget>false</displayOnWidget>
            </OSCArgument>
         </OSCMessage>
      </OSCBundle>
      <colors>
         <foreColor>-39424</foreColor>
         <backColor>-39936</backColor>
         <textColor>-16777216</textColor>
         <borderColor>-12566464</borderColor>
         <foreAlpha>255</foreAlpha>
         <backAlpha>255</backAlpha>
         <textAlpha>255</textAlpha>
         <borderAlpha>255</borderAlpha>
      </colors>
      <Z>5</Z>
      <X>374</X>
      <Y>77</Y>
      <width>39</width>
      <height>48</height>
      <borderwidth>2</borderwidth>
      <smoothingFactor>10.0</smoothingFactor>
      <rotation>0.0</rotation>
      <isTouchable>true</isTouchable>
      <displayName>true</displayName>
      <localFeedback>false</localFeedback>
      <isSliding>false</isSliding>
      <isRelative>false</isRelative>
      <contForeImg>false</contForeImg>
      <font>Arial-plain-12</font>
      <backgroundImage> </backgroundImage>
      <foregroundImage> </foregroundImage>
   </pad>
   <pad version="1.8" text="2">
      <OSCBundle>
         <OSCMessage>
            <OSCAddress>/sw/target2</OSCAddress>
            <OSCArgument version="1.2">
               <activeAxes>
                  <axis>
                     <number>1</number>
                     <active>false</active>
                  </axis>
                  <axis>
                     <number>2</number>
                     <active>false</active>
                  </axis>
                  <axis>
                     <number>3</number>
                     <active>false</active>
                  </axis>
               </activeAxes>
               <scalingAxes>
                  <axis>
                     <number>1</number>
                     <function>3</function>
                  </axis>
                  <axis>
                     <number>2</number>
                     <function>3</function>
                  </axis>
                  <axis>
                     <number>3</number>
                     <function>3</function>
                  </axis>
               </scalingAxes>
               <valueOfInteger>1</valueOfInteger>
               <refOfInteger>0</refOfInteger>
               <maxOfInteger>0</maxOfInteger>
               <defOfInteger>1</defOfInteger>
               <minOfInteger>0</minOfInteger>
               <isListening>false</isListening>
               <displayOnWidget>false</displayOnWidget>
            </OSCArgument>
         </OSCMessage>
      </OSCBundle>
      <colors>
         <foreColor>-1</foreColor>
         <backColor>-1</backColor>
         <textColor>-16777216</textColor>
         <borderColor>-12566464</borderColor>
         <foreAlpha>255</foreAlpha>
         <backAlpha>255</backAlpha>
         <textAlpha>255</textAlpha>
         <borderAlpha>255</borderAlpha>
      </colors>
      <Z>4</Z>
      <X>218</X>
      <Y>370</Y>
      <width>39</width>
      <height>48</height>
      <borderwidth>2</borderwidth>
      <smoothingFactor>10.0</smoothingFactor>
      <rotation>0.0</rotation>
      <isTouchable>true</isTouchable>
      <displayName>true</displayName>
      <localFeedback>false</localFeedback>
      <isSliding>false</isSliding>
      <isRelative>false</isRelative>
      <contForeImg>false</contForeImg>
      <font>Arial-plain-12</font>
      <backgroundImage> </backgroundImage>
      <foregroundImage> </foregroundImage>
   </pad>
   <pad version="1.8" text="T">
      <OSCBundle>
         <OSCMessage>
            <OSCAddress>/sw/upperLeftT</OSCAddress>
            <OSCArgument version="1.2">
               <activeAxes>
                  <axis>
                     <number>1</number>
                     <active>false</active>
                  </axis>
                  <axis>
                     <number>2</number>
                     <active>false</active>
                  </axis>
                  <axis>
                     <number>3</number>
                     <active>false</active>
                  </axis>
               </activeAxes>
               <scalingAxes>
                  <axis>
                     <number>1</number>
                     <function>3</function>
                  </axis>
                  <axis>
                     <number>2</number>
                     <function>3</function>
                  </axis>
                  <axis>
                     <number>3</number>
                     <function>3</function>
                  </axis>
               </scalingAxes>
               <valueOfInteger>1</valueOfInteger>
               <refOfInteger>0</refOfInteger>
               <maxOfInteger>0</maxOfInteger>
               <defOfInteger>1</defOfInteger>
               <minOfInteger>0</minOfInteger>
               <isListening>false</isListening>
               <displayOnWidget>false</displayOnWidget>
            </OSCArgument>
         </OSCMessage>
      </OSCBundle>
      <colors>
         <foreColor>-50116</foreColor>
         <backColor>-65536</backColor>
         <textColor>-1</textColor>
         <borderColor>-12566464</borderColor>
         <foreAlpha>255</foreAlpha>
         <backAlpha>255</backAlpha>
         <textAlpha>255</textAlpha>
         <borderAlpha>255</borderAlpha>
      </colors>
      <Z>27</Z>
      <X>132</X>
      <Y>225</Y>
      <width>39</width>
      <height>48</height>
      <borderwidth>2</borderwidth>
      <smoothingFactor>10.0</smoothingFactor>
      <rotation>310.0</rotation>
      <isTouchable>true</isTouchable>
      <displayName>true</displayName>
      <localFeedback>false</localFeedback>
      <isSliding>false</isSliding>
      <isRelative>false</isRelative>
      <contForeImg>false</contForeImg>
      <font>Arial-plain-12</font>
      <backgroundImage> </backgroundImage>
      <foregroundImage> </foregroundImage>
   </pad>
   <pad version="1.8" text="Outlane">
      <OSCBundle>
         <OSCMessage>
            <OSCAddress>/sw/outLaneLeft</OSCAddress>
            <OSCArgument version="1.2">
               <activeAxes>
                  <axis>
                     <number>1</number>
                     <active>false</active>
                  </axis>
                  <axis>
                     <number>2</number>
                     <active>false</active>
                  </axis>
                  <axis>
                     <number>3</number>
                     <active>false</active>
                  </axis>
               </activeAxes>
               <scalingAxes>
                  <axis>
                     <number>1</number>
                     <function>3</function>
                  </axis>
                  <axis>
                     <number>2</number>
                     <function>3</function>
                  </axis>
                  <axis>
                     <number>3</number>
                     <function>3</function>
                  </axis>
               </scalingAxes>
               <valueOfInteger>1</valueOfInteger>
               <refOfInteger>0</refOfInteger>
               <maxOfInteger>0</maxOfInteger>
               <defOfInteger>1</defOfInteger>
               <minOfInteger>0</minOfInteger>
               <isListening>false</isListening>
               <displayOnWidget>false</displayOnWidget>
            </OSCArgument>
         </OSCMessage>
      </OSCBundle>
      <colors>
         <foreColor>-50116</foreColor>
         <backColor>-65536</backColor>
         <textColor>-1</textColor>
         <borderColor>-12566464</borderColor>
         <foreAlpha>255</foreAlpha>
         <backAlpha>255</backAlpha>
         <textAlpha>255</textAlpha>
         <borderAlpha>255</borderAlpha>
      </colors>
      <Z>26</Z>
      <X>71</X>
      <Y>638</Y>
      <width>53</width>
      <height>48</height>
      <borderwidth>2</borderwidth>
      <smoothingFactor>10.0</smoothingFactor>
      <rotation>0.0</rotation>
      <isTouchable>true</isTouchable>
      <displayName>true</displayName>
      <localFeedback>false</localFeedback>
      <isSliding>false</isSliding>
      <isRelative>false</isRelative>
      <contForeImg>false</contForeImg>
      <font>Arial-plain-12</font>
      <backgroundImage> </backgroundImage>
      <foregroundImage> </foregroundImage>
   </pad>
   <pad version="1.8" text="Outlane">
      <OSCBundle>
         <OSCMessage>
            <OSCAddress>/sw/outlaneRight</OSCAddress>
            <OSCArgument version="1.2">
               <activeAxes>
                  <axis>
                     <number>1</number>
                     <active>false</active>
                  </axis>
                  <axis>
                     <number>2</number>
                     <active>false</active>
                  </axis>
                  <axis>
                     <number>3</number>
                     <active>false</active>
                  </axis>
               </activeAxes>
               <scalingAxes>
                  <axis>
                     <number>1</number>
                     <function>3</function>
                  </axis>
                  <axis>
                     <number>2</number>
                     <function>3</function>
                  </axis>
                  <axis>
                     <number>3</number>
                     <function>3</function>
                  </axis>
               </scalingAxes>
               <valueOfInteger>1</valueOfInteger>
               <refOfInteger>0</refOfInteger>
               <maxOfInteger>0</maxOfInteger>
               <defOfInteger>1</defOfInteger>
               <minOfInteger>0</minOfInteger>
               <isListening>false</isListening>
               <displayOnWidget>false</displayOnWidget>
            </OSCArgument>
         </OSCMessage>
      </OSCBundle>
      <colors>
         <foreColor>-50116</foreColor>
         <backColor>-65536</backColor>
         <textColor>-1</textColor>
         <borderColor>-12566464</borderColor>
         <foreAlpha>255</foreAlpha>
         <backAlpha>255</backAlpha>
         <textAlpha>255</textAlpha>
         <borderAlpha>255</borderAlpha>
      </colors>
      <Z>25</Z>
      <X>491</X>
      <Y>637</Y>
      <width>53</width>
      <height>48</height>
      <borderwidth>2</borderwidth>
      <smoothingFactor>10.0</smoothingFactor>
      <rotation>0.0</rotation>
      <isTouchable>true</isTouchable>
      <displayName>true</displayName>
      <localFeedback>false</localFeedback>
      <isSliding>false</isSliding>
      <isRelative>false</isRelative>
      <contForeImg>false</contForeImg>
      <font>Arial-plain-12</font>
      <backgroundImage> </backgroundImage>
      <foregroundImage> </foregroundImage>
   </pad>
   <pad version="1.8" text="Pop">
      <OSCBundle>
         <OSCMessage>
            <OSCAddress>/sw/jetBumper</OSCAddress>
            <OSCArgument version="1.2">
               <activeAxes>
                  <axis>
                     <number>1</number>
                     <active>false</active>
                  </axis>
                  <axis>
                     <number>2</number>
                     <active>false</active>
                  </axis>
                  <axis>
                     <number>3</number>
                     <active>false</active>
                  </axis>
               </activeAxes>
               <scalingAxes>
                  <axis>
                     <number>1</number>
                     <function>3</function>
                  </axis>
                  <axis>
                     <number>2</number>
                     <function>3</function>
                  </axis>
                  <axis>
                     <number>3</number>
                     <function>3</function>
                  </axis>
               </scalingAxes>
               <valueOfInteger>1</valueOfInteger>
               <refOfInteger>0</refOfInteger>
               <maxOfInteger>0</maxOfInteger>
               <defOfInteger>1</defOfInteger>
               <minOfInteger>0</minOfInteger>
               <isListening>false</isListening>
               <displayOnWidget>false</displayOnWidget>
            </OSCArgument>
         </OSCMessage>
      </OSCBundle>
      <colors>
         <foreColor>-50116</foreColor>
         <backColor>-65536</backColor>
         <textColor>-1</textColor>
         <borderColor>-12566464</borderColor>
         <foreAlpha>255</foreAlpha>
         <backAlpha>255</backAlpha>
         <textAlpha>255</textAlpha>
         <borderAlpha>255</borderAlpha>
      </colors>
      <Z>24</Z>
      <X>265</X>
      <Y>253</Y>
      <width>39</width>
      <height>48</height>
      <borderwidth>2</borderwidth>
      <smoothingFactor>10.0</smoothingFactor>
      <rotation>0.0</rotation>
      <isTouchable>true</isTouchable>
      <displayName>true</displayName>
      <localFeedback>false</localFeedback>
      <isSliding>false</isSliding>
      <isRelative>false</isRelative>
      <contForeImg>false</contForeImg>
      <font>Arial-plain-12</font>
      <backgroundImage> </backgroundImage>
      <foregroundImage> </foregroundImage>
   </pad>
   <pad version="1.8" text="O">
      <OSCBundle>
         <OSCMessage>
            <OSCAddress>/sw/upperLeftO</OSCAddress>
            <OSCArgument version="1.2">
               <activeAxes>
                  <axis>
                     <number>1</number>
                     <active>false</active>
                  </axis>
                  <axis>
                     <number>2</number>
                     <active>false</active>
                  </axis>
                  <axis>
                     <number>3</number>
                     <active>false</active>
                  </axis>
               </activeAxes>
               <scalingAxes>
                  <axis>
                     <number>1</number>
                     <function>3</function>
                  </axis>
                  <axis>
                     <number>2</number>
                     <function>3</function>
                  </axis>
                  <axis>
                     <number>3</number>
                     <function>3</function>
                  </axis>
               </scalingAxes>
               <valueOfInteger>1</valueOfInteger>
               <refOfInteger>0</refOfInteger>
               <maxOfInteger>0</maxOfInteger>
               <defOfInteger>1</defOfInteger>
               <minOfInteger>0</minOfInteger>
               <isListening>false</isListening>
               <displayOnWidget>false</displayOnWidget>
            </OSCArgument>
         </OSCMessage>
      </OSCBundle>
      <colors>
         <foreColor>-50116</foreColor>
         <backColor>-65536</backColor>
         <textColor>-1</textColor>
         <borderColor>-12566464</borderColor>
         <foreAlpha>255</foreAlpha>
         <backAlpha>255</backAlpha>
         <textAlpha>255</textAlpha>
         <borderAlpha>255</borderAlpha>
      </colors>
      <Z>23</Z>
      <X>158</X>
      <Y>189</Y>
      <width>39</width>
      <height>48</height>
      <borderwidth>2</borderwidth>
      <smoothingFactor>10.0</smoothingFactor>
      <rotation>310.0</rotation>
      <isTouchable>true</isTouchable>
      <displayName>true</displayName>
      <localFeedback>false</localFeedback>
      <isSliding>false</isSliding>
      <isRelative>false</isRelative>
      <contForeImg>false</contForeImg>
      <font>Arial-plain-12</font>
      <backgroundImage> </backgroundImage>
      <foregroundImage> </foregroundImage>
   </pad>
   <pad version="1.8" text="M">
      <OSCBundle>
         <OSCMessage>
            <OSCAddress>/sw/upperLeftM</OSCAddress>
            <OSCArgument version="1.2">
               <activeAxes>
                  <axis>
                     <number>1</number>
                     <active>false</active>
                  </axis>
                  <axis>
                     <number>2</number>
                     <active>false</active>
                  </axis>
                  <axis>
                     <number>3</number>
                     <active>false</active>
                  </axis>
               </activeAxes>
               <scalingAxes>
                  <axis>
                     <number>1</number>
                     <function>3</function>
                  </axis>
                  <axis>
                     <number>2</number>
                     <function>3</function>
                  </axis>
                  <axis>
                     <number>3</number>
                     <function>3</function>
                  </axis>
               </scalingAxes>
               <valueOfInteger>1</valueOfInteger>
               <refOfInteger>0</refOfInteger>
               <maxOfInteger>0</maxOfInteger>
               <defOfInteger>1</defOfInteger>
               <minOfInteger>0</minOfInteger>
               <isListening>false</isListening>
               <displayOnWidget>false</displayOnWidget>
            </OSCArgument>
         </OSCMessage>
      </OSCBundle>
      <colors>
         <foreColor>-50116</foreColor>
         <backColor>-65536</backColor>
         <textColor>-1</textColor>
         <borderColor>-12566464</borderColor>
         <foreAlpha>255</foreAlpha>
         <backAlpha>255</backAlpha>
         <textAlpha>255</textAlpha>
         <borderAlpha>255</borderAlpha>
      </colors>
      <Z>22</Z>
      <X>185</X>
      <Y>153</Y>
      <width>39</width>
      <height>48</height>
      <borderwidth>2</borderwidth>
      <smoothingFactor>10.0</smoothingFactor>
      <rotation>310.0</rotation>
      <isTouchable>true</isTouchable>
      <displayName>true</displayName>
      <localFeedback>false</localFeedback>
      <isSliding>false</isSliding>
      <isRelative>false</isRelative>
      <contForeImg>false</contForeImg>
      <font>Arial-plain-12</font>
      <backgroundImage> </backgroundImage>
      <foregroundImage> </foregroundImage>
   </pad>
   <pad version="1.8" text="C">
      <OSCBundle>
         <OSCMessage>
            <OSCAddress>/sw/upperRightC</OSCAddress>
            <OSCArgument version="1.2">
               <activeAxes>
                  <axis>
                     <number>1</number>
                     <active>false</active>
                  </axis>
                  <axis>
                     <number>2</number>
                     <active>false</active>
                  </axis>
                  <axis>
                     <number>3</number>
                     <active>false</active>
                  </axis>
               </activeAxes>
               <scalingAxes>
                  <axis>
                     <number>1</number>
                     <function>3</function>
                  </axis>
                  <axis>
                     <number>2</number>
                     <function>3</function>
                  </axis>
                  <axis>
                     <number>3</number>
                     <function>3</function>
                  </axis>
               </scalingAxes>
               <valueOfInteger>1</valueOfInteger>
               <refOfInteger>0</refOfInteger>
               <maxOfInteger>0</maxOfInteger>
               <defOfInteger>1</defOfInteger>
               <minOfInteger>0</minOfInteger>
               <isListening>false</isListening>
               <displayOnWidget>false</displayOnWidget>
            </OSCArgument>
         </OSCMessage>
      </OSCBundle>
      <colors>
         <foreColor>-16763905</foreColor>
         <backColor>-16776961</backColor>
         <textColor>-1</textColor>
         <borderColor>-12566464</borderColor>
         <foreAlpha>255</foreAlpha>
         <backAlpha>255</backAlpha>
         <textAlpha>255</textAlpha>
         <borderAlpha>255</borderAlpha>
      </colors>
      <Z>21</Z>
      <X>372</X>
      <Y>149</Y>
      <width>39</width>
      <height>48</height>
      <borderwidth>2</borderwidth>
      <smoothingFactor>10.0</smoothingFactor>
      <rotation>50.0</rotation>
      <isTouchable>true</isTouchable>
      <displayName>true</displayName>
      <localFeedback>false</localFeedback>
      <isSliding>false</isSliding>
      <isRelative>false</isRelative>
      <contForeImg>false</contForeImg>
      <font>Arial-plain-12</font>
      <backgroundImage> </backgroundImage>
      <foregroundImage> </foregroundImage>
   </pad>
   <pad version="1.8" text="T">
      <OSCBundle>
         <OSCMessage>
            <OSCAddress>/sw/upperRightT</OSCAddress>
            <OSCArgument version="1.2">
               <activeAxes>
                  <axis>
                     <number>1</number>
                     <active>false</active>
                  </axis>
                  <axis>
                     <number>2</number>
                     <active>false</active>
                  </axis>
                  <axis>
                     <number>3</number>
                     <active>false</active>
                  </axis>
               </activeAxes>
               <scalingAxes>
                  <axis>
                     <number>1</number>
                     <function>3</function>
                  </axis>
                  <axis>
                     <number>2</number>
                     <function>3</function>
                  </axis>
                  <axis>
                     <number>3</number>
                     <function>3</function>
                  </axis>
               </scalingAxes>
               <valueOfInteger>1</valueOfInteger>
               <refOfInteger>0</refOfInteger>
               <maxOfInteger>0</maxOfInteger>
               <defOfInteger>1</defOfInteger>
               <minOfInteger>0</minOfInteger>
               <isListening>false</isListening>
               <displayOnWidget>false</displayOnWidget>
            </OSCArgument>
         </OSCMessage>
      </OSCBundle>
      <colors>
         <foreColor>-16763905</foreColor>
         <backColor>-16776961</backColor>
         <textColor>-1</textColor>
         <borderColor>-12566464</borderColor>
         <foreAlpha>255</foreAlpha>
         <backAlpha>255</backAlpha>
         <textAlpha>255</textAlpha>
         <borderAlpha>255</borderAlpha>
      </colors>
      <Z>20</Z>
      <X>423</X>
      <Y>212</Y>
      <width>39</width>
      <height>48</height>
      <borderwidth>2</borderwidth>
      <smoothingFactor>10.0</smoothingFactor>
      <rotation>50.0</rotation>
      <isTouchable>true</isTouchable>
      <displayName>true</displayName>
      <localFeedback>false</localFeedback>
      <isSliding>false</isSliding>
      <isRelative>false</isRelative>
      <contForeImg>false</contForeImg>
      <font>Arial-plain-12</font>
      <backgroundImage> </backgroundImage>
      <foregroundImage> </foregroundImage>
   </pad>
</main>